{"chunk_definitions":[{"row":9,"row_count":1,"visible":true,"expansion_state":0,"options":{"engine":"r","label":"setup","include":false},"document_id":"775AFAB4","chunk_id":"csetup_chunk","chunk_label":"setup"},{"row":16,"row_count":1,"visible":true,"expansion_state":0,"options":{"engine":"r","label":"unnamed-chunk-3"},"document_id":"775AFAB4","chunk_id":"cztelw903v25w","chunk_label":"unnamed-chunk-1"},{"row":27,"row_count":1,"visible":true,"expansion_state":0,"options":{"engine":"r","label":"unnamed-chunk-23"},"document_id":"775AFAB4","chunk_id":"ccfy1guwnr6in","chunk_label":"unnamed-chunk-2"},{"row":37,"row_count":1,"visible":true,"expansion_state":0,"options":{"engine":"r","label":"unnamed-chunk-21"},"document_id":"775AFAB4","chunk_id":"czxeq7n2adn89","chunk_label":"unnamed-chunk-3"}],"doc_write_time":1668062925,"working_dir":null,"default_chunk_options":{"echo":true},"chunk_rendered_width":700}